packageten/__init__.py
packageten-0.1.dist-info/Licence.txt
packageten-0.1.dist-info/METADATA
packageten-0.1.dist-info/WHEEL
packageten-0.1.dist-info/top_level.txt
packageten-0.1.dist-info/RECORD
