Metadata-Version: 2.1
Name: packageten
Version: 0.1
Summary: this code can be used
Author: souj
License-File: Licence.txt
